vttcompilepy/_version.py
vttcompilepy/__init__.py
vttcompilepy/vttcompilepy.cpython-312-darwin.so
vttcompilepy/quit_to_glyphs.py
vttcompilepy/__main__.py
vttcompilepy-0.0.1.13.dist-info/RECORD
vttcompilepy-0.0.1.13.dist-info/WHEEL
vttcompilepy-0.0.1.13.dist-info/entry_points.txt
vttcompilepy-0.0.1.13.dist-info/top_level.txt
vttcompilepy-0.0.1.13.dist-info/METADATA
