Metadata-Version: 2.1
Name: vttcompilepy
Version: 0.0.1.13
Summary: Python extension for Visual TrueType font compile. 
Home-page: https://github.com/microsoft/VisualTrueType
Author: Paul Linnerud
Author-email: paulli@microsoft.com
License: MIT
Classifier: Programming Language :: Python :: 3
Classifier: License :: OSI Approved :: MIT License
Requires-Python: >=3.7
Requires-Dist: fonttools>=4.33.0
